RobotMongoDBLibrary/Delete.py
RobotMongoDBLibrary/Find.py
RobotMongoDBLibrary/Insert.py
RobotMongoDBLibrary/Update.py
RobotMongoDBLibrary/__init__.py
robot_mongodb_library-0.0.4.dist-info/METADATA
robot_mongodb_library-0.0.4.dist-info/WHEEL
robot_mongodb_library-0.0.4.dist-info/top_level.txt
robot_mongodb_library-0.0.4.dist-info/RECORD
