Metadata-Version: 2.1
Name: robot-mongodb-library
Version: 0.0.4
Summary: robotframework extension lib for test mongodb
Home-page: https://github.com/tarathep/robot-mongodb-library
Author: tarathep
Author-email: bokie.tarathep@gmail.com
License: MIT
Platform: UNKNOWN
Classifier: Programming Language :: Python :: 3
Classifier: License :: OSI Approved :: MIT License
Requires-Dist: pymongo
